f2p/__init__.py
f2p/core.py
f2p-0.1.1.dist-info/licenses/LICENSE
f2p-0.1.1.dist-info/METADATA
f2p-0.1.1.dist-info/WHEEL
f2p-0.1.1.dist-info/top_level.txt
f2p-0.1.1.dist-info/RECORD
